<?xml version="1.0" standalone="yes"?>

<Paper uid="C92-2080">
<Title>TRANSLATION AMBIGUITY RESOLUTION BASED ON TEXT CORPORA OF SOURCE AND TARGET LANGUAGES</Title>
<Section position="1" start_page="0" end_page="0" type="abstr">
<SectionTitle>
TRANSLATION AMBIGUITY RESOLUTION
BASED ON TEXT CORPORA
OF SOURCE AND TARGET LANGUAGES
</SectionTitle>
<Paragraph position="0"> Shinichi DOI and Kazunori MURAKI NEC Corp. C&amp;C Information Technology Research Laboratories 4 1 1, Miyazaki, Miyamae-ku, Kawasaki 216, JAPAN e-mail: doi%mtl.cl.nec.co.jl/~sj .nee. corn</Paragraph>
</Section>
</Paper>

